topsis_harshit_102303554/__init__.py
topsis_harshit_102303554/cli.py
topsis_harshit_102303554/core.py
topsis_harshit_kansal_102303554-1.0.1.dist-info/licenses/LICENSE
topsis_harshit_kansal_102303554-1.0.1.dist-info/METADATA
topsis_harshit_kansal_102303554-1.0.1.dist-info/WHEEL
topsis_harshit_kansal_102303554-1.0.1.dist-info/entry_points.txt
topsis_harshit_kansal_102303554-1.0.1.dist-info/top_level.txt
topsis_harshit_kansal_102303554-1.0.1.dist-info/RECORD
