Metadata-Version: 2.4
Name: topsis-harshit-kansal-102303554
Version: 1.0.1
Summary: TOPSIS (MCDM) implementation for ranking alternatives using multiple criteria.
Author: Harshit Kansal
Author-email: hkansal_be23@thapar.edu
Requires-Python: >=3.8
License-File: LICENSE
Requires-Dist: numpy
Requires-Dist: pandas
Dynamic: author
Dynamic: author-email
Dynamic: description
Dynamic: description-content-type
Dynamic: license-file
Dynamic: requires-dist
Dynamic: requires-python
Dynamic: summary
